logdiv/__init__.py
logdiv/divanalysis/__init__.py
logdiv/divanalysis/aggregated.py
logdiv/divanalysis/classification.py
logdiv/divanalysis/classification_folder.py
logdiv/divanalysis/cluster_classification.py
logdiv/divanalysis/function.py
logdiv/divanalysis/group_entropy.py
logdiv/divanalysis/matrix_calculator.py
logdiv/divanalysis/temporal.py
logdiv/file_functions/__init__.py
logdiv/file_functions/file_handlers.py
logdiv/file_functions/file_pkl.py
logdiv/file_functions/parameters_functions.py
logdiv/sessionfeatures/__init__.py
logdiv/sessionfeatures/features.py
logdiv/sessionfeatures/session_hist_tex.py
logdiv/sessionspaces/__init__.py
logdiv/sessionspaces/boxplots.py
logdiv/sessionspaces/cluster_mosaic.py
logdiv/sessionspaces/cluster_tex.py
logdiv/sessionspaces/clusterization.py
logdiv/sessionspaces/pca.py
logdiv/sessionspaces/plot_hist.py
logdiv/sessionspaces/transformation.py
logdiv/weblogtransform/__init__.py
logdiv/weblogtransform/classify.py
logdiv/weblogtransform/features.py
logdiv/weblogtransform/filters.py
logdiv/weblogtransform/pdtimestamp.py
logdiv/weblogtransform/plot_pages.py
logdiv/weblogtransform/sessionizer.py
logdiv/weblogtransform/weblog_tex.py
logdivv/__init__.py
logdivv/divanalysis/__init__.py
logdivv/divanalysis/aggregated.py
logdivv/divanalysis/classification.py
logdivv/divanalysis/cluster_classification.py
logdivv/divanalysis/function.py
logdivv/divanalysis/group_entropy.py
logdivv/divanalysis/matrix_calculator.py
logdivv/divanalysis/temporal.py
logdivv/file_functions/__init__.py
logdivv/file_functions/file_handlers.py
logdivv/file_functions/file_pkl.py
logdivv/file_functions/parameters_functions.py
logdivv/sessionfeatures/__init__.py
logdivv/sessionfeatures/features.py
logdivv/sessionfeatures/session_hist_tex.py
logdivv/sessionspaces/__init__.py
logdivv/sessionspaces/boxplots.py
logdivv/sessionspaces/cluster_mosaic.py
logdivv/sessionspaces/cluster_tex.py
logdivv/sessionspaces/clusterization.py
logdivv/sessionspaces/pca.py
logdiv-0.0.2.7.dist-info/LICENSE
logdiv-0.0.2.7.dist-info/METADATA
logdiv-0.0.2.7.dist-info/WHEEL
logdiv-0.0.2.7.dist-info/top_level.txt
logdiv-0.0.2.7.dist-info/RECORD
