Metadata-Version: 2.1
Name: logdiv
Version: 0.0.2.7
Summary: A package to mesure diversity of log files
Home-page: https://github.com/pedroramaciotti/diversity-patterns
Author: Alexandre Wilmet
Author-email: wilmet.alex@gmail.com
License: UNKNOWN
Platform: UNKNOWN
Classifier: Intended Audience :: Science/Research
Classifier: Programming Language :: Python
Classifier: Operating System :: Unix
